enkaliprime/__init__.py
enkaliprime/client.py
enkaliprime/client.pyi
enkaliprime/exceptions.py
enkaliprime/exceptions.pyi
enkaliprime/models.py
enkaliprime/models.pyi
enkaliprime/py.typed
enkaliprime/spinner.py
enkaliprime/spinner.pyi
enkaliprime/type_guards.py
enkaliprime/type_guards.pyi
enkaliprime-1.2.2.dist-info/licenses/LICENSE
enkaliprime-1.2.2.dist-info/METADATA
enkaliprime-1.2.2.dist-info/WHEEL
enkaliprime-1.2.2.dist-info/top_level.txt
enkaliprime-1.2.2.dist-info/RECORD
