Metadata-Version: 2.4
Name: enkaliprime
Version: 1.2.2
Summary: Python SDK for EnkaliPrime Chat API - RAG-enabled AI conversations
Author-email: EnkaliPrime <support@enkaliprime.com>
Maintainer-email: EnkaliPrime <support@enkaliprime.com>
License-Expression: MIT
Project-URL: Homepage, https://enkaliprime.com
Project-URL: Documentation, https://docs.enkaliprime.com
Project-URL: Repository, https://github.com/enkaliprime/python-sdk
Project-URL: Issues, https://github.com/enkaliprime/python-sdk/issues
Project-URL: Changelog, https://github.com/enkaliprime/python-sdk/blob/main/CHANGELOG.md
Keywords: enkaliprime,chat,ai,rag,chatbot,sdk,api,conversational-ai,llm
Classifier: Development Status :: 5 - Production/Stable
Classifier: Intended Audience :: Developers
Classifier: Operating System :: OS Independent
Classifier: Programming Language :: Python :: 3
Classifier: Programming Language :: Python :: 3.8
Classifier: Programming Language :: Python :: 3.9
Classifier: Programming Language :: Python :: 3.10
Classifier: Programming Language :: Python :: 3.11
Classifier: Programming Language :: Python :: 3.12
Classifier: Programming Language :: Python :: 3.13
Classifier: Topic :: Communications :: Chat
Classifier: Topic :: Internet :: WWW/HTTP :: Dynamic Content
Classifier: Topic :: Scientific/Engineering :: Artificial Intelligence
Classifier: Topic :: Software Development :: Libraries :: Python Modules
Classifier: Typing :: Typed
Requires-Python: >=3.8
License-File: LICENSE
Requires-Dist: httpx>=0.24.0
Requires-Dist: typing-extensions>=4.0.0
Provides-Extra: dev
Requires-Dist: pytest>=7.0.0; extra == "dev"
Requires-Dist: pytest-asyncio>=0.21.0; extra == "dev"
Requires-Dist: pytest-cov>=4.0.0; extra == "dev"
Requires-Dist: black>=23.0.0; extra == "dev"
Requires-Dist: isort>=5.12.0; extra == "dev"
Requires-Dist: mypy>=1.0.0; extra == "dev"
Requires-Dist: ruff>=0.0.280; extra == "dev"
Provides-Extra: docs
Requires-Dist: mkdocs>=1.5.0; extra == "docs"
Requires-Dist: mkdocs-material>=9.0.0; extra == "docs"
Requires-Dist: mkdocstrings[python]>=0.22.0; extra == "docs"
Dynamic: license-file
